{
  "id": "yb_esp32s3_amp_v3",
  "name": "YelloByte YB-ESP32-S3-AMP (Rev.3)",
  "platform": "espressif32",
  "mcu": "ESP32S3",
  "fcpu": 240000000,
  "ram": 327680,
  "rom": 8388608,
  "frameworks": [
    "arduino",
    "espidf"
  ],
  "vendor": "YelloByte",
  "url": "https://github.com/yellobyte/ESP32-DevBoards-Getting-Started/tree/main/boards/YB-ESP32-S3-AMP",
  "connectivity": [
    "wifi",
    "bluetooth"
  ],
  "debug": {
    "tools": {
      "cmsis-dap": {},
      "esp-prog": {},
      "esp-bridge": {},
      "iot-bus-jtag": {},
      "jlink": {},
      "minimodule": {},
      "olimex-arm-usb-tiny-h": {},
      "olimex-arm-usb-ocd-h": {},
      "olimex-arm-usb-ocd": {},
      "olimex-jtag-tiny": {},
      "tumpa": {},
      "esp-builtin": {}
    }
  }
}