{
  "id": "nucleo_f091rc",
  "name": "ST Nucleo F091RC",
  "platform": "ststm32",
  "mcu": "STM32F091RCT6",
  "fcpu": 48000000,
  "ram": 32768,
  "rom": 262144,
  "frameworks": [
    "arduino",
    "cmsis",
    "mbed",
    "stm32cube",
    "libopencm3",
    "zephyr"
  ],
  "vendor": "ST",
  "url": "https://developer.mbed.org/platforms/ST-Nucleo-F091RC/",
  "connectivity": [
    "can"
  ],
  "debug": {
    "tools": {
      "blackmagic": {},
      "jlink": {},
      "stlink": {
        "onboard": true,
        "default": true
      },
      "cmsis-dap": {}
    }
  },
  "build": {
    "extra_flags": "-DSTM32F0 -DSTM32F091xC",
    "core": "stm32",
    "f_cpu": "48000000L",
    "mcu": "stm32f091rct6",
    "variant": "STM32F0xx/F091RBT_F091RC(H-T-Y)"
  },
  "upload": {
    "protocol": "stlink"
  }
}
