{
  "build": {
    "arduino": {
      "ldscript": "nrf52840_s140_v6.ld"
    },
    "core": "nRF5",
    "extra_flags": "-DARDUINO_MDBT50Q_RX -DNRF52840_XXAA",
    "f_cpu": "64000000L",
    "mcu": "nrf52840",
    "variant": "raytac_mdbt50q_rx"
  },
  "connectivity": [
    "bluetooth"
  ],
  "debug": {
    "tools": {
      "blackmagic": {},
      "cmsis-dap": {},
      "jlink": {},
      "stlink": {}
    }
  },
  "fcpu": 64000000,
  "frameworks": [
    "arduino"
  ],
  "id": "raytac_mdbt50q_rx",
  "mcu": "NRF52840",
  "name": "Raytac MDBT50Q-RX Dongle",
  "platform": "nordicnrf52",
  "ram": 248832,
  "rom": 815104,
  "upload": {
    "maximum_ram_size": 248832,
    "maximum_size": 815104,
    "protocol": "nrfutil",
    "require_upload_port": true,
    "speed": 115200,
    "use_1200bps_touch": true,
    "wait_for_upload_port": true
  },
  "url": "https://www.raytac.com/product/ins.php?index_id=89",
  "vendor": "Raytac"
}
