{
  "build": {
    "arduino": {
      "ldscript": "esp32_out.ld"
    },
    "core": "esp32",
    "extra_flags": "-DARDUINO_ESP32_DEV",
    "f_cpu": "240000000L",
    "f_flash": "80000000L",
    "flash_mode": "qio",
    "mcu": "esp32",
    "variant": "sparkfun_lora_gateway_1-channel"
  },
  "connectivity": [
    "wifi",
    "bluetooth",
    "ethernet",
    "can"
  ],
  "debug": {
    "tools": {
      "cmsis-dap": {},
      "esp-prog": {},
      "iot-bus-jtag": {},
      "jlink": {},
      "minimodule": {},
      "olimex-arm-usb-ocd": {},
      "olimex-arm-usb-ocd-h": {},
      "olimex-arm-usb-tiny-h": {},
      "olimex-jtag-tiny": {},
      "tumpa": {}
    }
  },
  "fcpu": 240000000,
  "frameworks": [
    "arduino",
    "espidf"
  ],
  "id": "sparkfun_lora_gateway_1-channel",
  "mcu": "ESP32",
  "name": "SparkFun LoRa Gateway 1-Channel",
  "platform": "espressif32",
  "ram": 327680,
  "rom": 4194304,
  "upload": {
    "flash_size": "4MB",
    "maximum_ram_size": 327680,
    "maximum_size": 4194304,
    "require_upload_port": true,
    "speed": 460800
  },
  "url": "https://www.sparkfun.com/products/15006",
  "vendor": "SparkFun"
}
