{
  "build": {
    "core": "naked",
    "extra_flags": "-DSTC8C1KXX -DSTC8C1K08 -DNAKED_ARCH_MCS51 -DNAKED_MCS51_STC8C1KXX",
    "f_cpu": "11059200L",
    "mcu": "stc8c1k08",
    "variant": "stc8c1kxx"
  },
  "fcpu": 11059200,
  "frameworks": [],
  "id": "STC8C1K08",
  "mcu": "STC8C1K08",
  "name": "Generic STC8C1K08",
  "platform": "intel_mcs51",
  "ram": 1280,
  "rom": 8192,
  "upload": {
    "maximum_ram_size": 1280,
    "maximum_size": 8192,
    "protocol": "stcgal"
  },
  "url": "http://www.stcmicro.com/stc/stc51.html",
  "vendor": "STC"
}
